quick_llm/__init__.py
quick_llm/chain_endpoints.py
quick_llm/chain_factory.py
quick_llm/prompt_input_parser.py
quick_llm/rag_document_ingestor.py
quick_llm/type_definitions.py
quick_llm/chat/__init__.py
quick_llm/chat/api_chat_provider.py
quick_llm/chat/chain_chat_provider.py
quick_llm/chat/chat_provider.py
quick_llm/preprocessor/__init__.py
quick_llm/preprocessor/regex_document_layout.py
quick_llm/preprocessor/regex_preprocesor_loader.py
quick_llm_factory-0.1.1.dist-info/METADATA
quick_llm_factory-0.1.1.dist-info/WHEEL
quick_llm_factory-0.1.1.dist-info/top_level.txt
quick_llm_factory-0.1.1.dist-info/RECORD
