Metadata-Version: 2.4
Name: quick-llm-factory
Version: 0.1.1
Summary: Tools for quickly building and deploying large language model applications.
Requires-Python: >=3.13
Requires-Dist: langchain>=1.2.1
Requires-Dist: langchain-community>=0.4.1
Requires-Dist: langchain-core>=1.2.6
Requires-Dist: pydantic>=2.12.5
